radio/__init__.py
radio/analog/__init__.py
radio/analog/am.py
radio/analog/decimator.py
radio/analog/mfm.py
radio/analog/wbfm.py
radio/tools/__init__.py
radio/tools/helpers.py
radio/tools/pll/__init__.py
radio/tools/pll/_core.py
radio/tools/pll/_core_cuda.py
radio/tools/tuner/__init__.py
radio_core-0.2.2.dist-info/LICENSE
radio_core-0.2.2.dist-info/METADATA
radio_core-0.2.2.dist-info/WHEEL
radio_core-0.2.2.dist-info/top_level.txt
radio_core-0.2.2.dist-info/RECORD
