Metadata-Version: 2.1
Name: radio-core
Version: 0.2.2
Summary: Python based library for FM, AM and WBFM demodulation.
Home-page: https://github.com/luigifreitas/radio-core
Author: Luigi F. Cruz
Author-email: UNKNOWN
License: UNKNOWN
Platform: UNKNOWN
